{"commitInfo":{"timestamp":1696214671059,"operation":"WRITE","operationParameters":{"mode":"Overwrite","partitionBy":"[]"},"readVersion":0,"isolationLevel":"Serializable","isBlindAppend":false,"operationMetrics":{"numFiles":"1","numOutputRows":"5","numOutputBytes":"1807"},"engineInfo":"Apache-Spark/3.4.1 Delta-Lake/2.4.0","txnId":"8933ce90-41fe-4d12-9dfa-2647b9b8df44"}}
{"add":{"path":"part-00000-68e788f2-f46d-48e2-9bba-aae913e2fd97-c000.snappy.parquet","partitionValues":{},"size":1807,"modificationTime":1696214666726,"dataChange":true,"stats":"{\"numRecords\":5,\"minValues\":{\"firstname\":\"James\",\"middlename\":\"\",\"lastname\":\"\",\"id\":\"\",\"gender\":\"F\",\"salary\":-1},\"maxValues\":{\"firstname\":\"Robert\",\"middlename\":\"Rose\",\"lastname\":\"Williams\",\"id\":\"42114\",\"gender\":\"M\",\"salary\":4000},\"nullCount\":{\"firstname\":0,\"middlename\":0,\"lastname\":0,\"id\":0,\"gender\":0,\"salary\":0}}"}}
{"remove":{"path":"part-00003-72b001b4-9e63-4fc3-9cd9-3df55fc5b902-c000.snappy.parquet","deletionTimestamp":1696214671045,"dataChange":true,"extendedFileMetadata":true,"partitionValues":{},"size":1673}}
{"remove":{"path":"part-00002-b0be55ba-9d67-4c2d-a3eb-851a1fc433b3-c000.snappy.parquet","deletionTimestamp":1696214671047,"dataChange":true,"extendedFileMetadata":true,"partitionValues":{},"size":1676}}
{"remove":{"path":"part-00001-5038a5e0-0de0-4aea-9d9c-1a8ef1d30f25-c000.snappy.parquet","deletionTimestamp":1696214671047,"dataChange":true,"extendedFileMetadata":true,"partitionValues":{},"size":1655}}
{"remove":{"path":"part-00000-298d98df-96cb-4b9a-a4ea-9c44585b45d8-c000.snappy.parquet","deletionTimestamp":1696214671047,"dataChange":true,"extendedFileMetadata":true,"partitionValues":{},"size":1648}}
